sqlpt/__init__.py
sqlpt/__main__.py
sqlpt/service.py
sqlpt/sql.py
sqlpt-0.2.2.dist-info/LICENSE
sqlpt-0.2.2.dist-info/METADATA
sqlpt-0.2.2.dist-info/WHEEL
sqlpt-0.2.2.dist-info/entry_points.txt
sqlpt-0.2.2.dist-info/top_level.txt
sqlpt-0.2.2.dist-info/RECORD
