Metadata-Version: 2.1
Name: sqlpt
Version: 0.2.2
Summary: SQL Probing Tool
Author-email: Bryce Caine <brycecaine@gmail.com>
Project-URL: Homepage, https://github.com/brycecaine/sqlpt
Project-URL: Documentation, https://sqlpt.readthedocs.io
Keywords: sql,probing,tool,query
Classifier: Development Status :: 3 - Alpha
Classifier: Intended Audience :: Developers
Classifier: License :: OSI Approved :: MIT License
Classifier: Operating System :: OS Independent
Classifier: Programming Language :: Python
Classifier: Programming Language :: Python :: 3
Classifier: Topic :: Database :: Front-Ends
Requires-Python: >=3.7
License-File: LICENSE
Requires-Dist: sqlparse (>=0.4.2)
Requires-Dist: SQLAlchemy (>=1.4.40)
Requires-Dist: truth-table-generator (>=1.1.2)
